{"inkVersion":21,"root":[["^“任务已完成，塔可待命中。” ","#","^type:RightAvatarText ","/#","#","^speaker:Taco","/#","\n","^“……” ","#","^type:LeftAvatarText ","/#","#","^speaker:Doctor","/#","\n","^“……啊。” ","#","^type:LeftAvatarText ","/#","#","^speaker:Doctor","/#","\n","^“嗯，辛苦了，塔可。” ","#","^type:LeftAvatarText ","/#","#","^speaker:Doctor","/#","\n","^“你也可以休息了。” ","#","^type:LeftAvatarText ","/#","#","^speaker:Doctor","/#","\n","^“肯定。塔可将进入休眠模式。” ","#","^type:RightAvatarText ","/#","#","^speaker:Taco","/#","\n","^“……” ","#","^type:LeftAvatarText ","/#","#","^speaker:Doctor","/#","\n","^“……晚安。” ","#","^type:LeftAvatarText ","/#","#","^speaker:Doctor","/#","\n",["done",{"#f":5,"#n":"g-0"}],null],"done",{"#f":1}],"listDefs":{}}